skoot-0.20.0.dist-info/RECORD
skoot-0.20.0.dist-info/METADATA
skoot-0.20.0.dist-info/WHEEL
skoot-0.20.0.dist-info/top_level.txt
skoot/decorators.py
skoot/setup.py
skoot/base.py
skoot/__init__.py
skoot/impute.py
skoot/exceptions.py
skoot/__config__.py
skoot/preprocessing/skewness.py
skoot/preprocessing/encode.py
skoot/preprocessing/__init__.py
skoot/preprocessing/dates.py
skoot/preprocessing/binning.py
skoot/preprocessing/scale.py
skoot/preprocessing/schema.py
skoot/preprocessing/tests/test_dates.py
skoot/preprocessing/tests/test_scale.py
skoot/preprocessing/tests/test_binning.py
skoot/preprocessing/tests/__init__.py
skoot/preprocessing/tests/test_schema.py
skoot/preprocessing/tests/test_skewness.py
skoot/preprocessing/tests/test_encode.py
skoot/decomposition/setup.py
skoot/decomposition/__init__.py
skoot/decomposition/_dqrsl.cpython-36m-x86_64-linux-gnu.so
skoot/decomposition/decompose.py
skoot/decomposition/_dqrutl.py
skoot/decomposition/tests/__init__.py
skoot/decomposition/tests/test_qr.py
skoot/decomposition/tests/test_decompose.py
skoot/.libs/libgfortran-ed201abd.so.3.0.0
skoot/model_validation/__init__.py
skoot/model_validation/_validator.py
skoot/model_validation/tests/__init__.py
skoot/model_validation/tests/test_validators.py
skoot/__check_build/_check_build.cpython-36m-x86_64-linux-gnu.so
skoot/__check_build/setup.py
skoot/__check_build/__init__.py
skoot/__check_build/tests/__init__.py
skoot/__check_build/tests/test_check_build.py
skoot/feature_extraction/interact.py
skoot/feature_extraction/spatial.py
skoot/feature_extraction/base.py
skoot/feature_extraction/__init__.py
skoot/feature_extraction/dates.py
skoot/feature_extraction/tests/test_dates.py
skoot/feature_extraction/tests/__init__.py
skoot/feature_extraction/tests/test_interact.py
skoot/feature_extraction/tests/test_spatial.py
skoot/_lib/__init__.py
skoot/_lib/_testutils.py
skoot/utils/metaestimators.py
skoot/utils/dataframe.py
skoot/utils/testing.py
skoot/utils/compat.py
skoot/utils/_docstr.py
skoot/utils/iterables.py
skoot/utils/__init__.py
skoot/utils/profiling.py
